{
  "kind": "collectionType",
  "collectionName": "knowledges",
  "info": {
    "singularName": "knowledge",
    "pluralName": "knowledges",
    "displayName": "Knowledge",
    "description": ""
  },
  "options": {
    "draftAndPublish": true
  },
  "pluginOptions": {
    "i18n": {
      "localized": true
    }
  },
  "attributes": {
    "title": {
      "type": "string",
      "required": true,
      "pluginOptions": {
        "i18n": {
          "localized": true
        }
      }
    },
    "job": {
      "type": "relation",
      "relation": "manyToOne",
      "target": "api::job.job",
      "inversedBy": "knowledges"
    },
    "competency": {
      "type": "relation",
      "relation": "manyToOne",
      "target": "api::competency.competency",
      "inversedBy": "knowledges"
    },
    "section": {
      "type": "relation",
      "relation": "manyToOne",
      "target": "api::section.section",
      "inversedBy": "knowledges"
    },
    "profile": {
      "type": "relation",
      "relation": "manyToOne",
      "target": "api::profile.profile",
      "inversedBy": "knowledges"
    },
    "materials": {
      "type": "relation",
      "relation": "oneToMany",
      "target": "api::material.material",
      "mappedBy": "knowledge"
    }
  }
}
